pengent/__init__.py
pengent/agents/__init__.py
pengent/agents/agent_base.py
pengent/agents/basic/agent_chat.py
pengent/agents/basic/agent_coder.py
pengent/core/artifacts/artifact.py
pengent/core/artifacts/artifact_service/__init__.py
pengent/core/artifacts/artifact_service/base_artifact_service.py
pengent/core/artifacts/artifact_service/in_memory_artfact_service.py
pengent/core/artifacts/artifact_service/storage_artifact_service.py
pengent/core/message_memory/__init__.py
pengent/core/message_memory/history_message_memory.py
pengent/core/message_memory/message_memory.py
pengent/core/message_memory/retrieval_message_memory.py
pengent/core/message_memory/summary_message_memory.py
pengent/core/message_memory/storage/__init__.py
pengent/core/message_memory/storage/file_memory_storage.py
pengent/core/message_memory/storage/memory_storage_interface.py
pengent/core/message_memory/storage/redis_memory_storage.py
pengent/core/message_memory/vector/faissy_store.py
pengent/core/message_memory/vector/qdrant_store.py
pengent/core/message_memory/vector/vectore_store_factory.py
pengent/core/message_memory/vector/vectore_store_interface.py
pengent/core/runners/__init__.py
pengent/core/runners/runner.py
pengent/core/sessions/__init__.py
pengent/core/sessions/session.py
pengent/core/sessions/session_service/database_session_service.py
pengent/core/sessions/session_service/in_memory_session_service.py
pengent/core/sessions/session_service/redis_session_service.py
pengent/core/sessions/session_service/session_service_base.py
pengent/core/sessions/session_service/storage_session_service.py
pengent/db/base.py
pengent/db/models/messages_orm.py
pengent/db/models/session_orm.py
pengent/errors/already_exists_error.py
pengent/lib/__init__.py
pengent/lib/common.py
pengent/lib/custom_logger.py
pengent/lib/singleton.py
pengent/llm/__init__.py
pengent/llm/llm_client_anthropic.py
pengent/llm/llm_client_base.py
pengent/llm/llm_client_factory.py
pengent/llm/llm_client_gemini.py
pengent-1.2.1.dist-info/licenses/LICENSE
pengent-1.2.1.dist-info/METADATA
pengent-1.2.1.dist-info/WHEEL
pengent-1.2.1.dist-info/top_level.txt
pengent-1.2.1.dist-info/RECORD
