Metadata-Version: 2.4
Name: pengent
Version: 1.2.1
Summary: Genaral AI Angent Framework for Python
Author-email: ryoh Ya <dev.p.ry.yamafuji@gmail.com>, Pengent <ai.pengent@gmail.com>
License: MIT
Requires-Python: >=3.8
License-File: LICENSE
Requires-Dist: requests
Requires-Dist: openai>=1.71.0
Requires-Dist: python-dotenv>=1.0.1
Requires-Dist: pydantic==2.12.4
Requires-Dist: markdown>=3.7
Requires-Dist: pdfkit==1.0.0
Requires-Dist: redis>=7.1.0
Requires-Dist: sqlalchemy>=2.0.45
Requires-Dist: mcp==1.10.1
Dynamic: license-file
